LICENSE
MANIFEST.in
README.md
requirements.txt
setup.py
examples/auth_std_libraries/README.md
examples/auth_std_libraries/auth_std_HILIC_pos_12_01_2024_JM_wMS2.csv
examples/auth_std_libraries/auth_std_RP_neg_12_01_2024_JM_wMS2.csv
examples/configurations/khipu_isotopes./up_to_three_groups.json
examples/filters/README.md
examples/filters/drop_dda.json
examples/filters/hilicneg.json
examples/filters/hilicpos.json
examples/filters/qaqc_drop.json
examples/filters/rpneg.json
examples/filters/rppos.json
examples/report_templates/README.md
examples/report_templates/default_batch_corrected.json
examples/report_templates/default_w_tics.json
examples/report_templates/minimal.json
examples/workflows/.DS_Store
examples/workflows/README.md
examples/workflows/bash_workflows/.DS_Store
examples/workflows/bash_workflows/README.md
examples/workflows/bash_workflows/generic/basic_processing_no_AcquireX.sh
examples/workflows/bash_workflows/generic/basic_processing_no_AcquireX_noFilter.sh
examples/workflows/bash_workflows/generic/basic_processing_w_AcquireX.sh
examples/workflows/bash_workflows/generic/minimal_processing.sh
examples/workflows/bash_workflows/generic/two_chromatography_modes_using_filters.sh
examples/workflows/bash_workflows/manuscript/.DS_Store
examples/workflows/bash_workflows/manuscript/Ansone_2021.sh
examples/workflows/bash_workflows/manuscript/Bowen_2023_cell.sh
examples/workflows/bash_workflows/manuscript/Checkmate.sh
examples/workflows/bash_workflows/manuscript/Checkmate_subset.sh
examples/workflows/bash_workflows/manuscript/HZV029_HILIC_subset.sh
examples/workflows/bash_workflows/manuscript/HZV029_QC.sh
examples/workflows/bash_workflows/manuscript/HZV029_RP_subset.sh
examples/workflows/bash_workflows/manuscript/HZV029_plasma_HILIC.sh
examples/workflows/bash_workflows/manuscript/HZV029_plasma_RP.sh
examples/workflows/bash_workflows/manuscript/HZV029_plasma_RP_batch_correct.sh
examples/workflows/bash_workflows/manuscript/HZV029_two_phase_HILIC.sh
pcpfm.egg-info/PKG-INFO
pcpfm.egg-info/SOURCES.txt
pcpfm.egg-info/dependency_links.txt
pcpfm.egg-info/entry_points.txt
pcpfm.egg-info/requires.txt
pcpfm.egg-info/top_level.txt
