Metadata-Version: 2.1
Name: pcpfm
Version: 1.1.2
Summary: LC-MS metabolomics data processing pipeline
Home-page: https://github.com/jmmitc06/PythonCentricPipelineForMetabolomics
Author: Joshua Mitchell
Author-email: joshua.mitchell@jax.org
License: MIT
Keywords: metabolomics bioinformatics mass spectrometry
Classifier: Intended Audience :: Developers
Classifier: Intended Audience :: Science/Research
Classifier: License :: OSI Approved :: BSD License
Classifier: Natural Language :: English
Classifier: Operating System :: OS Independent
Classifier: Programming Language :: Python :: 3
Classifier: Topic :: Scientific/Engineering :: Bio-Informatics
Classifier: Topic :: Scientific/Engineering :: Chemistry
Classifier: Topic :: Software Development :: Libraries :: Python Modules
Requires-Python: >=3.7
License-File: LICENSE
